deletefb/__init__.py
deletefb/__main__.py
deletefb/deletefb.py
deletefb/exceptions.py
deletefb/logging_conf.json
deletefb/quit_driver.py
deletefb/types.py
deletefb/version.py
deletefb/tools/__init__.py
deletefb/tools/archive.py
deletefb/tools/chrome_driver.py
deletefb/tools/comments.py
deletefb/tools/common.py
deletefb/tools/config.py
deletefb/tools/conversations.py
deletefb/tools/likes.py
deletefb/tools/login.py
deletefb/tools/wall.py
delete_facebook_posts-1.1.17.dist-info/LICENSE
delete_facebook_posts-1.1.17.dist-info/METADATA
delete_facebook_posts-1.1.17.dist-info/WHEEL
delete_facebook_posts-1.1.17.dist-info/entry_points.txt
delete_facebook_posts-1.1.17.dist-info/top_level.txt
delete_facebook_posts-1.1.17.dist-info/RECORD
