Metadata-Version: 2.1
Name: delete-facebook-posts
Version: 1.1.17
Summary: A Selenium Script to Delete Facebook Posts
Home-page: https://github.com/weskerfoot/DeleteFB
Author: Wesley Kerfoot
Author-email: wes@wesk.tech
License: UNKNOWN
Platform: UNKNOWN
Classifier: Programming Language :: Python :: 3
Classifier: License :: OSI Approved :: MIT License
Classifier: Operating System :: OS Independent
Requires-Dist: selenium
Requires-Dist: selenium-requests
Requires-Dist: requests
Requires-Dist: pybloom-live
Requires-Dist: attrs
Requires-Dist: cattrs-3.8
Requires-Dist: lxml
Requires-Dist: pendulum
Requires-Dist: clint
Requires-Dist: progressbar
Requires-Dist: appdirs
